datasend/__init__.py
datasend-0.1.0.dist-info/METADATA
datasend-0.1.0.dist-info/WHEEL
datasend-0.1.0.dist-info/top_level.txt
datasend-0.1.0.dist-info/RECORD
