Metadata-Version: 2.4
Name: datasend
Version: 0.1.0
Summary: The quickest way to share data with your team
Home-page: https://bigdatalab.ai
Author: DataShare Team
Author-email: p.korovesis@bigdatalab.ai
Classifier: Development Status :: 3 - Alpha
Classifier: Intended Audience :: Developers
Classifier: Programming Language :: Python :: 3
Classifier: Programming Language :: Python :: 3.7
Classifier: Programming Language :: Python :: 3.8
Classifier: Programming Language :: Python :: 3.9
Requires-Python: >=3.7
Dynamic: author
Dynamic: author-email
Dynamic: classifier
Dynamic: description
Dynamic: description-content-type
Dynamic: home-page
Dynamic: requires-python
Dynamic: summary
